[
    {
        "q_id":"stack_heap",
        "q_title":"变量存放位置",
        "q_subtitle":"（堆区、栈区、常量区）",
        "showNextPage": false,
        "showArticle":true,
        "function":"testStackHeap",
    },
    {
        "q_id":"100",
        "q_title":"block参数捕获原理",
        "q_subtitle":"",
        "showNextPage": false,
        "showArticle":true,
        "function":"testBlock_catch",
    },
    {
        "q_id":"101",
        "q_title":"堆区、栈区block捕获strong变量",
        "q_subtitle":"",
        "showNextPage": false,
        "showArticle":true,
        "function":"testBlock_catch_strong",
    },
    {
        "q_id":"102",
        "q_title":"栈区block捕获weak变量",
        "q_subtitle":"",
        "showNextPage": false,
        "showArticle":true,
        "function":"testBlock_catch_weak",
    },
    {
        "q_id":"102",
        "q_title":"栈区block捕获__block变量",
        "q_subtitle":"",
        "showNextPage": false,
        "showArticle":true,
        "function":"testBlock_catch_block",
    },
    
    {
        "q_id":"103",
        "q_title":"面试题：这段代码是否存在问题？",
        "q_subtitle":"",
        "showNextPage": false,
        "showArticle":true,
        "function":"testBlock_weak_strong",
    },
    {
        "q_id":"104",
        "q_title":"__block的作用",
        "q_subtitle":"",
        "showNextPage": false,
        "showArticle":true,
        "function":"testBlockKeyWord_block",
    },
    
]
 
